pfund_plot/__init__.py
pfund_plot/cli/__init__.py
pfund_plot/cli/commands/config.py
pfund_plot/cli/commands/plot.py
pfund_plot/cli/main.py
pfund_plot/composites/composite.py
pfund_plot/config_handler.py
pfund_plot/const/enums/__init__.py
pfund_plot/const/enums/dashboard_type.py
pfund_plot/const/enums/data_type.py
pfund_plot/const/enums/dataframe_backend.py
pfund_plot/const/enums/display_mode.py
pfund_plot/const/enums/notebook_type.py
pfund_plot/const/enums/plotting_backend.py
pfund_plot/const/paths.py
pfund_plot/exports/__init__.py
pfund_plot/layout.py
pfund_plot/main.py
pfund_plot/mosaic.py
pfund_plot/plots/candlestick.py
pfund_plot/plots/dataframe.py
pfund_plot/plots/line.py
pfund_plot/plots/orderbook.py
pfund_plot/renderer.py
pfund_plot/templates/__init__.py
pfund_plot/templates/dashboard.py
pfund_plot/templates/notebook.py
pfund_plot/templates/spreadsheet.py
pfund_plot/templates/template.py
pfund_plot/types/core.py
pfund_plot/types/literals.py
pfund_plot/utils/utils.py
pfund_plot/utils/validate.py
pfund_plot-0.0.1.dev3.dist-info/LICENSE
pfund_plot-0.0.1.dev3.dist-info/METADATA
pfund_plot-0.0.1.dev3.dist-info/WHEEL
pfund_plot-0.0.1.dev3.dist-info/entry_points.txt
pfund_plot-0.0.1.dev3.dist-info/RECORD
