Metadata-Version: 2.1
Name: pfund-plot
Version: 0.0.1.dev3
Summary: A library for financial data visualization, dashboard creation, and template sharing.
Home-page: https://pfund.ai
License: Apache-2.0
Keywords: financial data,plotting,dashboards,charts,data visualization,graphs,plots
Author: stephenyau
Author-email: softwareentrepreneer+pfund-plot@gmail.com
Requires-Python: >=3.10,<4.0
Classifier: Intended Audience :: Developers
Classifier: Intended Audience :: Financial and Insurance Industry
Classifier: Intended Audience :: Information Technology
Classifier: Intended Audience :: Science/Research
Classifier: License :: OSI Approved :: Apache Software License
Classifier: Operating System :: OS Independent
Classifier: Programming Language :: Python :: 3
Classifier: Programming Language :: Python :: 3.10
Classifier: Programming Language :: Python :: 3.11
Classifier: Programming Language :: Python :: 3.12
Classifier: Programming Language :: Python :: 3.13
Classifier: Topic :: Office/Business :: Financial :: Investment
Classifier: Topic :: Scientific/Engineering :: Visualization
Classifier: Topic :: Software Development :: Libraries
Provides-Extra: all
Provides-Extra: dash
Provides-Extra: gradio
Provides-Extra: solara
Provides-Extra: streamlit
Provides-Extra: taipy
Requires-Dist: dash (>=2.18.1,<3.0.0) ; extra == "dash" or extra == "all"
Requires-Dist: gradio (>=5.9.1,<6.0.0) ; extra == "gradio" or extra == "all"
Requires-Dist: hvplot[datashader,plotly] (>=0.11.2,<0.12.0)
Requires-Dist: jupyter-bokeh (>=4.0.5,<5.0.0)
Requires-Dist: narwhals (>=1.19.1,<2.0.0)
Requires-Dist: panel (>=1.5.5,<2.0.0)
Requires-Dist: papermill (>=2.6.0,<3.0.0)
Requires-Dist: pfeed (>=0.0.2,<0.0.3)
Requires-Dist: pywebview (>=5.3.2,<6.0.0)
Requires-Dist: streamlit (>=1.41.1,<2.0.0) ; extra == "streamlit" or extra == "all"
Requires-Dist: taipy (>=4.0.0,<5.0.0) ; extra == "taipy" or extra == "all"
Requires-Dist: voila (>=0.5.8,<0.6.0)
Project-URL: Documentation, https://pfund-plot-docs.pfund.ai
Project-URL: Repository, https://github.com/PFund-Software-Ltd/pfund-plot
